{"3": "<*>", "193": "Deleting", "142": "BLOCK*", "29": "<*>", "150": "<*>", "101": "<*>", "57": "Deleting", "118": "<*>", "128": "Deleting", "194": "<*>", "164": "Deleting", "44": "BLOCK*", "97": "Deleting", "48": "Deleting", "17": "<*>", "52": "Deleting", "89": "<*>", "20": "<*>", "95": "/<*>/blk_<*>", "165": "<*>", "8": "<*>", "59": "BLOCK*", "24": "<*>", "182": "Deleting", "132": "BLOCK*", "137": "Deleting", "54": "<*>", "63": "<*>", "141": "<*>", "135": "<*>", "14": "Deleting", "170": "BLOCK*", "186": "Receiving", "55": "<*>", "13": "<*>", "35": "BLOCK*", "167": "/<*>", "152": "<*>", "76": "BLOCK*", "28": "<*>", "106": "Deleting", "191": "Deleting", "93": "/<*>/blk_<*>", "174": "Received", "184": "Received", "156": "<*>", "25": "terminating", "171": "/<*>", "159": "BLOCK*", "2": "<*>", "178": "<*>", "31": "<*>", "124": "Receiving", "183": "terminating", "173": "<*>", "37": "<*>", "22": "<*>", "12": "PacketResponder", "140": "<*>", "56": "Deleting", "39": "BLOCK*", "19": "<*>", "154": "BLOCK*", "155": "<*>", "100": "BLOCK*", "117": "<*>", "96": "/<*>", "4": "Receiving", "70": "<*>", "5": "<*>", "153": "Received", "47": "Deleting", "36": "<*>", "189": "Received", "32": "<*>", "23": "Deleting", "77": "<*>", "51": "<*>", "42": "/<*>", "66": "<*>", "108": "BLOCK*", "38": "<*>", "79": "<*>", "27": "<*>", "65": "<*>", "82": "/<*>/blk_<*>", "102": "Deleting", "179": "<*>", "74": "Received", "123": "<*>", "130": "<*>", "9": "<*>", "71": "<*>", "91": "<*>", "6": "<*>", "80": "<*>", "58": "BLOCK*", "115": "<*>", "83": "Deleting", "121": "<*>", "86": "<*>", "78": "<*>", "75": "<*>", "134": "<*>", "192": "<*>", "34": "/<*>/blk_<*>", "45": "BLOCK*", "104": "Deleting", "163": "BLOCK*", "114": "Receiving", "62": "Received", "87": "<*>", "92": "Deleting", "109": "<*>", "126": "Receiving", "185": "Received", "43": "Received", "160": "blk_<*>", "110": "terminating", "161": "BLOCK*", "157": "<*>", "61": "succeeded", "162": "/<*>", "122": "Deleting", "49": "<*>", "166": "<*>", "181": "<*>", "190": "<*>", "195": "BLOCK*", "99": "BLOCK*", "60": "<*>", "26": "<*> <*> Served block blk_<*> to /<*>", "103": "BLOCK*", "148": "<*>", "176": "BLOCK*", "129": "<*>", "188": "Received", "139": "<*>", "15": "Received", "1": "BLOCK*", "81": "<*>", "131": "BLOCK*", "113": "<*>", "175": "Deleting", "127": "<*>", "33": "<*>", "158": "BLOCK*", "172": "Deleting", "144": "Receiving", "84": "BLOCK*", "30": "<*>", "169": "BLOCK*", "133": "Deleting", "149": "Deleting", "187": "BLOCK*", "46": "BLOCK*", "180": "<*>", "90": "Deleting", "112": "<*>", "72": "Received", "107": "BLOCK*", "10": "/<*>/blk_<*>", "177": "Deleting", "105": "BLOCK*", "53": "<*>", "125": "<*>", "67": "BLOCK*", "116": "/<*>/blk_<*>", "94": "Received", "73": "<*>", "197": "<*>", "138": "<*>", "145": "<*>", "147": "<*>", "68": "<*>", "7": "<*>", "168": "<*>", "11": "Deleting", "111": "BLOCK*", "143": "Deleting", "18": "Receiving", "88": "Received", "50": "<*>", "16": "Deleting", "21": "Deleting", "41": "<*>", "198": "<*>", "85": "<*>", "136": "BLOCK*", "98": "<*>", "69": "<*>", "151": "<*>", "119": "BLOCK*", "196": "<*>", "146": "<*>", "40": "<*>", "120": "<*>", "64": "Receiving"}