{"78": "<*>", "36": "Input", "67": "<*>)", "70": "<*>", "106": "Found", "64": "<*>", "101": "Running", "73": "<*>)", "39": "Partition", "35": "<*>", "82": "<*>)", "55": "Saved", "42": "<*>,", "95": "<*>", "119": "Finished", "19": "<*>)", "4": "<*>", "51": "<*>", "89": "Running", "109": "Running", "45": "<*>", "85": "<*>", "92": "<*>)", "83": "<*>)", "93": "<*>)", "98": "Running", "112": "Finished", "76": "<*>)", "66": "<*>, free <*>)", "94": "<*>", "105": "<*>, free <*>)", "115": "<*>,", "110": "<*>)", "88": "<*>)", "72": "<*>,", "86": "<*>)", "49": "<*>", "26": "<*>, free <*>)", "11": "<*>", "3": "<*>)", "5": "<*>,", "60": "<*>, free <*>)", "30": "<*>", "15": "<*>)", "48": "<*>, free <*>)", "24": "Running", "71": "<*>)", "104": "<*>", "22": "<*>, free <*>)", "80": "<*>)", "21": "Finished", "13": "<*>", "27": "<*>", "96": "<*>)", "57": "<*>, free <*>)", "44": "<*>)", "6": "<*>)", "107": "<*>)", "16": "<*>)", "90": "<*>)", "33": "Saved", "37": "Finished", "34": "<*>)", "99": "<*>)", "87": "Running", "41": "<*>,", "14": "<*>, free <*>)", "1": "<*>", "65": "Finished", "118": "Found", "113": "<*>, free <*>)", "100": "Finished", "58": "Found", "77": "Running", "17": "<*>", "12": "Running", "40": "Finished", "29": "Finished", "108": "<*>", "111": "<*>,", "10": "<*>)", "114": "Finished", "50": "<*>)", "68": "Finished", "2": "<*>)", "79": "Finished", "62": "<*>", "84": "<*>", "61": "<*>)", "116": "<*>, free <*>)", "54": "Finished", "20": "<*>)", "43": "<*>", "69": "<*>, free <*>)", "56": "<*>)", "38": "<*>)", "59": "<*>", "120": "<*>)", "25": "<*>", "46": "<*>)", "32": "<*>)", "103": "<*>", "53": "<*>)", "117": "<*>)", "31": "<*>)", "47": "<*>)", "28": "<*>)", "7": "<*>)", "23": "Running", "52": "<*>, free <*>)", "8": "<*>)", "74": "Partition", "102": "<*>", "18": "<*>, free <*>)", "91": "Partition", "63": "<*>)", "9": "<*>", "81": "<*>,", "75": "<*>)", "97": "Finished"}